spotapi/__init__.py
spotapi/album.py
spotapi/artist.py
spotapi/client.py
spotapi/creator.py
spotapi/family.py
spotapi/login.py
spotapi/password.py
spotapi/player.py
spotapi/playlist.py
spotapi/podcast.py
spotapi/public.py
spotapi/song.py
spotapi/status.py
spotapi/user.py
spotapi/websocket.py
spotapi/_tests/__init__.py
spotapi/_tests/annotations_test.py
spotapi/data/__init__.py
spotapi/data/data.py
spotapi/data/interfaces.py
spotapi/exceptions/__init__.py
spotapi/exceptions/errors.py
spotapi/http/__init__.py
spotapi/http/data.py
spotapi/http/request.py
spotapi/solvers/__init__.py
spotapi/solvers/capmonster.py
spotapi/solvers/capsolver.py
spotapi/types/__init__.py
spotapi/types/alias.py
spotapi/types/annotations.py
spotapi/types/data.py
spotapi/types/interfaces.py
spotapi/utils/__init__.py
spotapi/utils/logger.py
spotapi/utils/saver.py
spotapi/utils/strings.py
spotapi-1.2.7.dist-info/LICENSE
spotapi-1.2.7.dist-info/METADATA
spotapi-1.2.7.dist-info/WHEEL
spotapi-1.2.7.dist-info/top_level.txt
spotapi-1.2.7.dist-info/RECORD
