Metadata-Version: 2.1
Name: spotapi
Version: 1.2.7
Summary: A sleek API wrapper for Spotify's private API
Home-page: UNKNOWN
Author: Aran
License: UNKNOWN
Keywords: Spotify,API,Spotify API,Spotify Private API,Follow,Like,Creator,Music,Music API,Streaming,Music Data,Track,Playlist,Album,Artist,Music Search,Music Metadata,SpotAPI,Python Spotify Wrapper,Music Automation,Web Scraping,Python Music API,Spotify Integration,Spotify Playlist,Spotify Tracks
Platform: UNKNOWN
License-File: LICENSE
Requires-Dist: requests
Requires-Dist: colorama
Requires-Dist: Pillow
Requires-Dist: readerwriterlock
Requires-Dist: tls-client
Requires-Dist: typing-extensions
Requires-Dist: validators
Requires-Dist: pyotp
Requires-Dist: beautifulsoup4
Provides-Extra: pymongo
Requires-Dist: pymongo ; extra == 'pymongo'
Provides-Extra: redis
Requires-Dist: redis ; extra == 'redis'
Provides-Extra: websocket
Requires-Dist: websockets ; extra == 'websocket'
